dwq/__init__.py
dwq/cmdserver.py
dwq/dwq-cat.py
dwq/dwq-drain.py
dwq/dwq-localjob.py
dwq/dwq.py
dwq/dwq_localjob.py
dwq/dwqc.py
dwq/dwqm.py
dwq/dwqr.py
dwq/dwqw.py
dwq/gitjobdir.py
dwq/selsubproc.py
dwq/util.py
dwq/version.py
dwq-0.1.0.dist-info/LICENSE
dwq-0.1.0.dist-info/METADATA
dwq-0.1.0.dist-info/WHEEL
dwq-0.1.0.dist-info/entry_points.txt
dwq-0.1.0.dist-info/top_level.txt
dwq-0.1.0.dist-info/RECORD
