Metadata-Version: 2.1
Name: dwq
Version: 0.1.0
Summary: dwq: a Disque based work queue
Home-page: https://github.com/kaspar030/dwq
Author: Kaspar Schleiser
Author-email: kaspar@schleiser.de
License: GPLv3
Keywords: distributed queue
Classifier: Development Status :: 3 - Alpha
Classifier: Intended Audience :: Developers
Classifier: Topic :: Software Development :: Build Tools
Classifier: License :: OSI Approved :: MIT License
Classifier: Programming Language :: Python :: 3.3
Classifier: Programming Language :: Python :: 3.4
Classifier: Programming Language :: Python :: 3.5
License-File: LICENSE
Requires-Dist: pydisque-dwq
